[
  {
    "year": 1901,
    "dynasty": "清朝",
    "emperor": "清德宗载湉 (光绪二十七年)",
    "events": [
      {
        "title": "清廷被迫签署辛丑条约国家主权严重沦丧",
        "category": "外交朝贡",
        "desc": "光绪二十七年七月，面对八国联军攻陷北京之亡国惨局，清廷被迫与英美法德意日俄奥等十一国代表，正式签署了屈辱至极之《辛丑条约》，赔款四亿五千万两白银，设立使馆界，拆毁大沽炮台。这一灾难性的外交朝贡体系彻底终结，使得中国完全沦为半殖民地半封建社会的深渊。",
        "isMajor": true
      }
    ]
  },
  {
    "year": 1902,
    "dynasty": "清朝",
    "emperor": "清德宗载湉 (光绪二十八年)",
    "events": [
      {
        "title": "慈禧太后与光绪皇帝起銮回銮北京整肃朝政",
        "category": "政权更迭",
        "desc": "光绪二十八年正月初三，逃亡西安一年有余之慈禧太后与光绪皇帝载湉，起銮大举回銮北京，重新大掌朝政权力中枢。为挽救摇摇欲坠的专制统治，清廷正式颁布多道谕旨，下令推行缓和满汉矛盾之“清末新政”，在一定程度上大举放宽对工商自耕农桑政策，图谋苟延残喘。"
      }
    ]
  },
  {
    "year": 1903,
    "dynasty": "清朝",
    "emperor": "清德宗载湉 (光绪二十九年)",
    "events": [
      {
        "title": "留日青年邹容撰写革命军在上海英租界刊行",
        "category": "政权更迭",
        "desc": "光绪二十九年，杰出青年革命家邹容在日本东京写成《革命军》一书，大举回到上海并在大集市公开雕版刊行。该书以极具煽动性与华夏文心之热血词藻，大声疾呼推翻满清封建帝制，大举建立独立民主之“中华共和国”。这一合理的革命宣传大潮，极大凝聚了天下志士文心，威震中枢。"
      }
    ]
  },
  {
    "year": 1904,
    "dynasty": "清朝",
    "emperor": "清德宗载湉 (光绪三十年)",
    "events": [
      {
        "title": "日俄战争在东北领土惨烈爆发清廷宣布中立",
        "category": "军事战役",
        "desc": "光绪三十年二月，日本与沙皇俄国为争夺在中国东北地缘之殖民霸权，悍然爆发日俄战争，两军在旅顺港及奉天平原隘口展开惨烈堑壕血战。腐朽的清廷竟然正式下圣旨宣布“局外中立”，导致辽东自耕农家园尽毁，饱受战火蹂躏。这一耻辱的国防失守，进一步激化了国内反帝革命大潮。"
      }
    ]
  },
  {
    "year": 1905,
    "dynasty": "清朝",
    "emperor": "清德宗载湉 (光绪三十一年)",
    "events": [
      {
        "title": "清廷宣布废除科举制度千年科考退出历史舞台",
        "category": "科举儒典",
        "desc": "光绪三十一年八月，为顺应近代救国变法大局并培养新型实业人才，袁世凯、张之洞等联名上奏，光绪皇帝正式下圣旨宣布“自丙午科为始，所有乡会试一律停止”，废除沿袭一千三百载之科举制度。这一科举儒典的划时代变革，彻底打碎了儒生士子的旧梦，大开中西近代教育之河。",
        "isMajor": true
      }
    ]
  },
  {
    "year": 1906,
    "dynasty": "清朝",
    "emperor": "清德宗载湉 (光绪三十二年)",
    "events": [
      {
        "title": "清廷下诏预备立宪大举改革中央六部官制",
        "category": "政权更迭",
        "desc": "光绪三十二年七月，迫于国内立宪派与革命派的双重政治重压，慈禧太后与光绪帝正式下圣旨宣布“预备立宪”，并大举启动了对中央六部官制的大改革，合并衙门，设立资政院。这一合理的政权更迭以图自救举措，虽然博得部分汉臣好评，但因满洲贵族集权专制本质而沦为骗局。"
      }
    ]
  },
  {
    "year": 1907,
    "dynasty": "清朝",
    "emperor": "清德宗载湉 (光绪三十三年)",
    "events": [
      {
        "title": "革命先驱秋瑾在绍兴大举起义失败壮烈就义",
        "category": "政权更迭",
        "desc": "光绪三十三年五月，杰出女革命家秋瑾与徐锡麟在浙江绍兴、安徽安庆秘密组织反清起义，由于叛徒出卖，秋瑾不幸在绍兴大通学堂被捕。面对严刑拷打，秋瑾留下了“秋风秋雨愁煞人”之千古绝唱，在绍兴轩亭口大举慷慨就义。这一血腥的政权更迭镇压，彻底唤醒了江南千万文心。"
      }
    ]
  },
  {
    "year": 1908,
    "dynasty": "清朝",
    "emperor": "清末帝溥仪 (宣统元年前夜)",
    "events": [
      {
        "title": "光绪帝与慈禧太后去世溥仪登基改元宣统",
        "category": "政权更迭",
        "desc": "光绪三十四年十月，光绪皇帝载湉与慈禧太后在二十四小时内相继在北京驾崩，享年分别为三十八岁与七十四岁。三岁之醇亲王载沣之子溥仪，奉太皇太后遗诏登基即位，改元“宣统”。这一重大的政权更迭，标志着大清帝国失去了最后的专制铁腕，无可挽回地走向崩塌。"
      }
    ]
  },
  {
    "year": 1909,
    "dynasty": "清朝",
    "emperor": "清末帝溥仪 (宣统元年)",
    "events": [
      {
        "title": "詹天佑主持修建之京张铁路全线完工大功告成",
        "category": "科技发明",
        "desc": "宣统元年八月，由杰出总工程师詹天佑亲自主持、完全自主设计并动工兴建之“京张铁路”，比原计划大举提前两年全线大功告成。詹天佑在陡峭关隘独创“人”字形折返轨道及先进榫卯技术，彻底打破了西方列强对中国铁路建设的垄断。这一科技发明的伟大胜利，极大提振了国人文心。"
      }
    ]
  },
  {
    "year": 1910,
    "dynasty": "清朝",
    "emperor": "清末帝溥仪 (宣统二年)",
    "events": [
      {
        "title": "东北爆发特大肺鼠疫伍连德建立铁血隔离防线",
        "category": "社会民生",
        "desc": "宣统二年冬，东北多省突发特大强烈肺鼠疫，死者累万，自耕农流离失所，社会民生极为危机。清廷紧急委任留英医学博士伍连德亲赴哈尔滨督导，伍连德采用近代先进的口罩隔离、火化遗体与海关铁血封港等防灾科技发明，用时数月大平定疫情，保全了千万平民性命。"
      }
    ]
  },
  {
    "year": 1911,
    "dynasty": "清朝",
    "emperor": "清末帝溥仪 (宣统三年)",
    "events": [
      {
        "title": "武昌起义爆发各省响应辛亥革命推翻封建帝制",
        "category": "政权更迭",
        "desc": "宣统三年八月十九日，革命党人在湖北武昌新军营盘毅然开枪起义，神速攻占总督衙门，武昌起义爆发。全国各直省纷纷响应，大举宣布脱离大清独立，史称“辛亥革命”。这一伟大的政权更迭巨变，以雷霆万钧之力，彻底推翻了统治中国两千余年的封建君主专制制度，功标青史。",
        "isMajor": true
      }
    ]
  },
  {
    "year": 1912,
    "dynasty": "中华民国",
    "emperor": "临时大总统孙中山 (民国元年)",
    "events": [
      {
        "title": "孙中山就任临时大总统中华民国在南京成立",
        "category": "政权更迭",
        "desc": "民国元年正月初一，杰出革命领袖孙中山在南京宣誓就职临时大总统，宣告中华民国正式成立。二月，清宣统帝溥仪正式下圣旨颁布退位诏书，大清帝国大功告成灭亡。这一重大的政权更迭，标志着中国历史正式翻开了崭新纪元，主权回归人民，大中华民族思想空前大解放。",
        "isMajor": true
      }
    ]
  },
  {
    "year": 1913,
    "dynasty": "中华民国",
    "emperor": "大总统袁世凯 (民国二年)",
    "events": [
      {
        "title": "宋教仁在上海遇刺身亡孙中山发起二次革命",
        "category": "政权更迭",
        "desc": "民国二年三月，国民党代理理事长宋教仁在上海火车站惨遭袁世凯暗中大举刺杀，震动全国。七月，为捍卫共和成果，孙中山在南方毅然发起“二次革命”讨伐袁世凯。由于北洋军力雄厚，讨袁军在江西隘口等地交火失利，革命运动被迫转入地下，袁世凯彻底大举把持中枢权力。"
      }
    ]
  },
  {
    "year": 1914,
    "dynasty": "中华民国",
    "emperor": "大总统袁世凯 (民国三年)",
    "events": [
      {
        "title": "一战爆发日军强行占领青岛强推山东特权",
        "category": "军事战役",
        "desc": "民国三年八月，第一次世界大战在大欧洲惨烈爆发，日本借口对德宣战，派遣海陆军强行在中国山东龙口登岸，攻占青岛要塞，抢掠胶济铁路沿线自耕农。袁世凯政府妥协退让，划定“交战区”。这一灾难性的海防与领土主权丧失，暴露了北洋政府在列强环伺下的地缘软弱无力。"
      }
    ]
  },
  {
    "year": 1915,
    "dynasty": "中华民国",
    "emperor": "大总统袁世凯 (民国四年)",
    "events": [
      {
        "title": "新文化运动在上海爆发陈独秀创办青年杂志",
        "category": "文化交流",
        "desc": "民国四年九月，杰出学者陈独秀在上海创办《青年杂志》，大举高举“民主”与“科学”两面旗帜，新文化运动轰轰烈烈大爆发。同平，袁世凯被迫接受日本丧权辱国之“二十一条”。这一合理的文化交流与思想启蒙大潮，极大地唤醒了海内外知识分子的爱国文心，功在启蒙。",
        "isMajor": true
      }
    ]
  },
  {
    "year": 1916,
    "dynasty": "中华民国",
    "emperor": "大总统袁世凯 (民国五年)",
    "events": [
      {
        "title": "袁世凯复辟帝制失败在全国唾骂中病逝",
        "category": "政权更迭",
        "desc": "民国五年三月，自封“洪宪皇帝”的袁世凯，在全国护国军讨伐与大集市罢市的漫天唾骂声中，被迫大举宣告取消帝制。六月，袁世凯在极度绝望中因尿毒症病逝，享年五十七岁。这一重大的政权更迭风波，标志着复辟帝制阴谋彻底破产，中国政治正式进入了北洋军阀割据混战之深渊。"
      }
    ]
  },
  {
    "year": 1917,
    "dynasty": "中华民国",
    "emperor": "北洋政府 (段祺瑞/黎元洪) (民国六年)",
    "events": [
      {
        "title": "辫子军张勋复辟宣统帝段祺瑞起兵神速平叛",
        "category": "政权更迭",
        "desc": "民国六年六月，北洋督军张勋大举率领三千“辫子军”突入京师，强行大举复辟退位之宣统帝溥仪，震动朝野。国务总理段祺瑞迅速在马厂誓师讨逆，统率大兵在京畿关隘大破辫子军，复辟闹剧仅维持十二日便烟消云散。这一合理的政权更迭铁血平定，捍卫了民国共和之法统。"
      }
    ]
  },
  {
    "year": 1918,
    "dynasty": "中华民国",
    "emperor": "北洋政府 (徐世昌) (民国七年)",
    "events": [
      {
        "title": "蔡元培主政北京大学倡导兼容并包思想自由",
        "category": "文化交流",
        "desc": "民国七年，一代大儒蔡元培正式出任北京大学校长，大举倡导“思想自由，兼容并包”之学术治校原则，提携了李大钊、胡适等一批卓越俊杰。北京大学成为中国近代史上最具活力的文化交流中心。这一合理的学术改革，不仅极大地繁荣了科学研究，也为五四运动埋下了最炽烈的火种。"
      }
    ]
  },
  {
    "year": 1919,
    "dynasty": "中华民国",
    "emperor": "北洋政府 (徐世昌) (民国八年)",
    "events": [
      {
        "title": "五四爱国运动在北京爆发全国自耕农齐心响应",
        "category": "社会民生",
        "desc": "民国八年五月四日，因大国在巴黎和会上外交惨败，北京三千余名爱国学子愤然走上街头，火烧赵家楼，大举痛击卖国贼，五四爱国运动爆发。全国大集市工商业罢市，自耕农万众响应。这一合理的爱国社会运动，不仅极大捍卫了海疆防线与地缘主权，也彻底大举弘扬了觉醒之文心。",
        "isMajor": true
      }
    ]
  },
  {
    "year": 1920,
    "dynasty": "中华民国",
    "emperor": "北洋政府 (徐世昌) (民国九年)",
    "events": [
      {
        "title": "直皖战争在京津外围爆发直系军阀控制京师",
        "category": "军事战役",
        "desc": "民国九年七月，为争夺北洋中枢掌控权，直系军阀曹锟、吴佩孚与皖系军阀段祺瑞，在京津外围隘口大举打响了惨烈的“直皖战争”。两军动用西洋火炮铁甲大兵，战火延烧数省，波及千万自耕农桑生计。直军在奉系支持下迅速获胜，直系掌权，拉开了民国初年军阀大战大序幕。"
      }
    ]
  },
  {
    "year": 1921,
    "dynasty": "中华民国",
    "emperor": "孙中山 (非常大总统) (民国十年)",
    "events": [
      {
        "title": "中国共产党在上海正式成立开天辟地启新航",
        "category": "政权更迭",
        "desc": "民国十年七月，中国共产党第一次全国代表大会在上海法租界秘密召开，后转移至浙江嘉兴南湖红船上，中国共产党宣告正式成立。大会大一统确立了推翻资产阶级、实现共产主义之伟大奋斗目标。这一极其重大的政权更迭事件，成为中华民族历史上惊天动地之开天辟地起点。",
        "isMajor": true
      }
    ]
  },
  {
    "year": 1922,
    "dynasty": "中华民国",
    "emperor": "孙中山 (非常大总统) (民国十一年)",
    "events": [
      {
        "title": "陈炯明兵变袭扰孙中山在永丰舰脱险图自强",
        "category": "政权更迭",
        "desc": "民国十一年六月，粤军总司令陈炯明背信弃义，在广州悍然发动武装兵变，炮轰总统府。孙中山被迫大举转移至永丰舰（后改中山舰）指挥反击，历经数十日惊险历程方脱险北上。这一重大的政权更迭风波，促使孙中山深刻反思军事策略，立志大举改组国民党并筹建黄埔军校。"
      }
    ]
  },
  {
    "year": 1923,
    "dynasty": "中华民国",
    "emperor": "北洋政府 (曹锟) (民国十二年)",
    "events": [
      {
        "title": "京汉铁路二七大罢工爆发直系军阀血腥镇压",
        "category": "社会民生",
        "desc": "民国十二年二月，为争取民主工会权利，京汉铁路全体工人大举发起惊天动地之“二七大罢工”，全线铁路瘫痪，严重打击了北洋商业贸易运输。直系军阀吴佩孚下令血腥镇压，制造二七惨案，杀害工会领袖林祥谦。这一合理的社会民生维权斗争，展现了工人阶级不可侮之铁骨文心。"
      }
    ]
  },
  {
    "year": 1924,
    "dynasty": "中华民国",
    "emperor": "北洋政府 (段祺瑞) (民国十三年)",
    "events": [
      {
        "title": "国民党一大在广州隆重举行开启国共首度合作",
        "category": "政权更迭",
        "desc": "民国十三年一月，孙中山在广州正式主持召开国民党第一次全国代表大会，重新大一统阐释了三民主义，确立了“联俄、联共、扶助农工”之三大革命政策，国共第一次合作宣告成型。同年，黄埔军校破土动工，这一重大的政权更迭与革命军事动员，大举掀起了国民革命大高潮。"
      }
    ]
  },
  {
    "year": 1925,
    "dynasty": "中华民国",
    "emperor": "北洋政府 (段祺瑞) (民国十四年)",
    "events": [
      {
        "title": "孙中山在北京病逝全国大集市降半旗隆重致哀",
        "category": "社会民生",
        "desc": "民国十四年三月十二日，中华民国国父、杰出革命先驱孙中山在北京因肝癌不幸逝世，享年五十九岁。临终留下“革命尚未成功，同志仍须努力”之伟大遗嘱。全国直省降半旗，数百万自耕农与市民自发赴吊。这一重大的社会民生悲剧，使得中国革命阵营失去了共同的灯塔。"
      }
    ]
  },
  {
    "year": 1926,
    "dynasty": "中华民国",
    "emperor": "北洋政府 (顾维钧) (民国十五年)",
    "events": [
      {
        "title": "国民革命军誓师北伐横扫两湖大破吴佩孚主力",
        "category": "军事战役",
        "desc": "民国十五年七月，国民革命军十万大兵在广州誓师，正式大举开启“北伐战争”。在叶挺独立团等北伐先锋拼死血战下，北伐军在大平原与贺胜桥隘口大破直系吴佩孚主力军，乘胜攻占武昌，自耕农夹道欢迎。这一重大的军事战役大捷，沉重打击了北洋割据，威震神州。"
      }
    ]
  },
  {
    "year": 1927,
    "dynasty": "中华民国",
    "emperor": "国民政府 (蒋中正) (民国十六年)",
    "events": [
      {
        "title": "南昌起义爆发中国共产党独立领导之军队诞生",
        "category": "政权更迭",
        "desc": "民国十六年八月一日，面对国民党蒋介石在上海发动的“四一二”血腥政变，周恩来、朱德、贺龙等在江西南昌毅然大举打响了反抗国民党反动派的第一枪，南昌起义大爆发。这一重大的政权更迭与军事战役起点，宣告了中国共产党独立领导的人民军队正式诞生，铁骨傲骨顶天立地。",
        "isMajor": true
      }
    ]
  },
  {
    "year": 1928,
    "dynasty": "中华民国",
    "emperor": "国民政府 (蒋中正) (民国十七载)",
    "events": [
      {
        "title": "张学良宣布东北易帜国民政府名义上一统",
        "category": "政权更迭",
        "desc": "民国十七年十二月，继张作霖皇姑屯遇刺被德军——不，被日军炸死后，其子张学良将军力排日本干涉巨压，在奉天通电正式宣布“东北易帜”，服从南京国民政府。这一合理的政权更迭与地缘行政大改制，宣告了大清覆灭后中国名义上的大一统宣告达成，暂时稳定了国防边界。"
      }
    ]
  },
  {
    "year": 1929,
    "dynasty": "中华民国",
    "emperor": "国民政府 (蒋中正) (民国十八年)",
    "events": [
      {
        "title": "科学家在周口店发现首个北京人头盖骨化石",
        "category": "科技发明",
        "desc": "民国十八年，中国杰出青年考古学家斐文中，在北平周口店发掘中，极其敏锐地发现并剥离出了首个完整的“北京人头盖骨化石”，震惊了全球人类学与古生物学界。这一伟大的科技发明与考古发现，将东亚人类起源史神速向前大举推进了数十万平，功在科学，名留千秋。"
      }
    ]
  },
  {
    "year": 1930,
    "dynasty": "中华民国",
    "emperor": "国民政府 (蒋中正) (民国十九年)",
    "events": [
      {
        "title": "中原大战在河南平原爆发蒋冯阎李数百万血战",
        "category": "军事战役",
        "desc": "民国十九年五月，为争夺南京国民政府中央极权，蒋介石与冯玉祥、阎锡山、李宗仁，在河南平原与陇海铁路隘口打响了中国近代史上规模最大之军阀内战“中原大战”。双方动用大兵百万，波及数省自耕农生计，死伤数十万。这一重大的军事战役使得中原大地赤地千里，民生维艰。"
      }
    ]
  },
  {
    "year": 1931,
    "dynasty": "中华民国",
    "emperor": "国民政府 (蒋中正) (民国二十年)",
    "events": [
      {
        "title": "九一八事变爆发日军奇袭沈阳侵占东北全境",
        "category": "军事战役",
        "desc": "民国二十年九月十八日夜，日本关东军悍然炸毁沈阳柳条湖段南满铁路，反诬中国军队所为，随即炮轰东北军北大营，九一八事变爆发。因蒋介石下令不抵抗，日军神速占领沈阳，进而吞并东北三省全境，奴役万千自耕农。这一重大的军事战役与领土沉沦，拉开了华夏十四年抗战大序幕。",
        "isMajor": true
      }
    ]
  },
  {
    "year": 1932,
    "dynasty": "中华民国",
    "emperor": "国民政府 (蒋中正) (民国二十一年)",
    "events": [
      {
        "title": "一二八淞沪抗战打响十九路军誓死抗击日寇",
        "category": "军事战役",
        "desc": "民国二十一年一月二十八日，日军在上海闸北挑起冲突，发起奇袭。爱国将领蒋光鼐、蔡廷锴亲率“十九路军”将士奋起大举抗击，在街巷、大滩及壕沟隘口与日军血战数月，屡败强敌，极大提振了全国抗日文心。这一重大的军事战役反击，展现了中华儿女不畏强暴之民族气节。"
      }
    ]
  },
  {
    "year": 1933,
    "dynasty": "中华民国",
    "emperor": "国民政府 (蒋中正) (民国二十二年)",
    "events": [
      {
        "title": "长城抗战爆发二十九军大刀队喜峰口大破日军",
        "category": "军事战役",
        "desc": "民国二十二年三月，为抵御日军强攻长城各关隘，二十九军将士在宋哲元、赵登禹指挥下，发起长城抗战。爱国官兵在喜峰口关隘赤膊血战，手持中原钢制大刀，在夜色中突入敌营砍杀日寇数百，威震中外，大鼓华夏文心。这一重大的军事战役胜利，保全了华北国防大门。"
      }
    ]
  },
  {
    "year": 1934,
    "dynasty": "中华民国",
    "emperor": "国民政府 (蒋中正) (民国二十三年)",
    "events": [
      {
        "title": "红军第五次反围剿失利被迫开始两万五千里长征",
        "category": "军事战役",
        "desc": "民国二十三年十月，由于王明博古“左”倾冒险主义错误，中央红军未能大举打破国民党军之第五次铁血围剿，被迫撤离江西中央革命根据地，宣告大举开始举世闻名的“两万五千里红军长征”，长途跃进。这一极其重大的军事战役战略大转移，拉开了中国革命火种万里播撒之序幕。",
        "isMajor": true
      }
    ]
  },
  {
    "year": 1935,
    "dynasty": "中华民国",
    "emperor": "国民政府 (蒋中正) (民国二十四年)",
    "events": [
      {
        "title": "遵义会议在贵州召开确立毛泽东之领导地位",
        "category": "政权更迭",
        "desc": "民国二十四年一月，长征途中的中国共产党在贵州遵义召开了政治局扩大会议，正式纠正了军事上的左倾错误，实际上大一统确立了毛泽东同志在党中央和红军中的终极核心领导地位。这一极其重大的政权更迭与生死交接，在危急关头挽救了红军，成为中国革命转危为安的伟大转折点。",
        "isMajor": true
      }
    ]
  },
  {
    "year": 1936,
    "dynasty": "中华民国",
    "emperor": "国民政府 (蒋中正) (民国二十五年)",
    "events": [
      {
        "title": "西安事变兵谏蒋介石大一统抗日战线基本确立",
        "category": "政权更迭",
        "desc": "民国二十五年十二月十二日，爱国将领张学良、杨虎城在西安毅然发动“兵谏”，扣押了蒋介石，要求停止内战、一致抗日，西安事变爆发。周恩来赴西安大举促成和平解决。这一合理的政权更迭消隐风波，结束了十年内战，大一统促成了抗日民族统一战线的基本成型，功标青史。"
      }
    ]
  },
  {
    "year": 1937,
    "dynasty": "中华民国",
    "emperor": "国民政府 (蒋中正) (民国二十六年)",
    "events": [
      {
        "title": "七七卢沟桥事变全面爆发全民族抗战铁血大开",
        "category": "军事战役",
        "desc": "民国二十六年七月七日夜，日军在北平西南宛平城卢沟桥挑起冲突，强攻县城，七七事变爆发。中国守军二十九军将士在桥头石狮旁大举开枪反击。蒋介石在庐山发表讲话，全民族抗战全面铁血大开，国共再度携手合作。这一极其重大的军事战役，宣告了大中华反抗法西斯之生死战开打。",
        "isMajor": true
      }
    ]
  },
  {
    "year": 1938,
    "dynasty": "中华民国",
    "emperor": "国民政府 (蒋中正) (民国二十七年)",
    "events": [
      {
        "title": "李宗仁取得台儿庄大捷重创侵华日军精锐大兵",
        "category": "军事战役",
        "desc": "民国二十七年三月，第五战区司令官李宗仁指挥中国大军，在山东台儿庄与日军板垣、矶谷精锐铁甲师团展开决死隘口激战。中国守军以长城血性，歼灭日军万余，台儿庄大捷震惊中外。这一合理的军事战役胜利，是中国全民族抗战爆发以来正面战场取得之最伟大之胜利，极大鼓舞了民心。"
      }
    ]
  },
  {
    "year": 1939,
    "dynasty": "中华民国",
    "emperor": "国民政府 (蒋中正) (民国二十八年)",
    "events": [
      {
        "title": "日军强渡黄河进犯边区八路军河道隘口死守",
        "category": "军事战役",
        "desc": "民国二十八年，日寇为大举切断陕甘宁边区抗日生命线，调集重兵配以飞机大炮强渡黄河天险，发起多次猛烈进犯。八路军将士在陕北黄河河畔与自耕农并肩作战，在黄河隘口大举设防死守，坚决击退敌军渡河企图。这一重大的军事战役保卫战，巩固了抗日大后方的绝对安全。"
      }
    ]
  },
  {
    "year": 1940,
    "dynasty": "中华民国",
    "emperor": "国民政府 (蒋中正) (民国二十九年)",
    "events": [
      {
        "title": "彭德怀指挥百团大战在华北交通线大破日伪",
        "category": "军事战役",
        "desc": "民国二十九年八月，八路军副总指挥彭德怀在华北地缘，动员了一百零五个团共二十余万大兵，发起威震敌胆之“百团大战”。清剿日寇据点，破袭铁路，毙伤日伪军四万余人。这一重大的军事战役大捷，给绝望中的日寇以致命打击，极大地大举坚定了全国军民抗战必胜之文心。",
        "isMajor": true
      }
    ]
  },
  {
    "year": 1941,
    "dynasty": "中华民国",
    "emperor": "国民政府 (蒋中正) (民国三十年)",
    "events": [
      {
        "title": "皖南事变爆发新四军将士惨遭反动派包围袭击",
        "category": "政权更迭",
        "desc": "民国三十年一月，蒋介石反动集团倒行逆施，密令大军在安徽泾县云岭隘口，悍然包围伏击了奉命北撤之新四军军部及将士九千余人，军长叶挺被俘，新四军损失惨重，皖南事变爆发。周恩来极其悲愤题词“千古奇冤”。这一重大的政权更迭与摩擦，导致抗日统一战线蒙上巨大阴霾。"
      }
    ]
  },
  {
    "year": 1942,
    "dynasty": "中华民国",
    "emperor": "国民政府 (蒋中正) (民国三十一年)",
    "events": [
      {
        "title": "河南爆发特大强烈旱蝗天灾饥荒自耕农惨绝",
        "category": "社会民生",
        "desc": "民国三十一年，中原河南直省遭遇了百年不遇之特大强烈干旱与疯狂蝗灾，赤地千里，桑蚕农桑彻底颗粒无收。国民党政府贪墨腐败，强征军粮，导致大批自耕农在饥寒交迫中饿死，千万难民流离失所，社会民生极为危机。这一毁灭性的社会民生惨剧，彻底埋葬了反动政权的底层合法性。"
      }
    ]
  },
  {
    "year": 1943,
    "dynasty": "中华民国",
    "emperor": "国民政府 (蒋中正) (民国三十二年)",
    "events": [
      {
        "title": "中美英签署开罗宣言明确战后台湾主权归还",
        "category": "外交朝贡",
        "desc": "民国三十二年十一月，中国领袖与美、英首脑在埃及开罗大举举行峰会，正式签署并发表了《开罗宣言》。宣言明确标定：战后日本必须将窃取自大中华之东北、台湾、澎湖列岛等神圣领土，大一统归还中国。这一宏伟的外交朝贡与主权博弈胜利，从国际法层面上大一统确立了国家主权。"
      }
    ]
  },
  {
    "year": 1944,
    "dynasty": "中华民国",
    "emperor": "国民政府 (蒋中正) (民国三十三年)",
    "events": [
      {
        "title": "豫湘桂会战大爆发国民党大军兵败如山倒防线破",
        "category": "军事战役",
        "desc": "民国三十三年，日军孤注一掷发动贯穿中国南北之“一号作战”（豫湘桂会战）。国民党军队贪腐严重、指挥极其无能，在日军攻势下兵败如山倒，丧失国土数十万平方公里，丢失城市数十座，波及自耕农千百。这一灾难性的军事战役惨败，彻底大举暴露了蒋介石独裁统治之腐朽不堪。"
      }
    ]
  },
  {
    "year": 1945,
    "dynasty": "中华民国",
    "emperor": "国民政府 (蒋中正) / 中国共产党 (民国三十四年)",
    "events": [
      {
        "title": "日本宣告无条件投降抗日战争取得伟大历史性大捷",
        "category": "军事战役",
        "desc": "民国三十四年八月十五日，法西斯日本裕仁天皇正式颁布退位——不，正式颁布投降诏书，宣告无条件投降。九月二日，日本在美军战舰上正式签署投降书，十四年浴血抗战胜利。这一重大的军事战役终极胜利，是中国近代百余年来反抗外来侵略、洗雪国耻之最伟大历史性大捷，功彪史册。",
        "isMajor": true
      }
    ]
  },
  {
    "year": 1946,
    "dynasty": "中华民国",
    "emperor": "国民政府 (蒋中正) (民国三十五年)",
    "events": [
      {
        "title": "全面内战打响国民党大兵强攻中原解放区隘口",
        "category": "军事战役",
        "desc": "民国三十五年六月，蒋介石悍然撕毁双十协定，调集美械大兵三十余万，对中原解放区隘口发起狂暴进攻，全面内战正式打响。中国人民解放军展开自卫反击。这一重大的军事战役爆发，将饱经蹂躏之自耕农平民再次推向了血雨腥风之深渊，国共两党政权更迭大对决正式开启。"
      }
    ]
  },
  {
    "year": 1947,
    "dynasty": "中华民国",
    "emperor": "国民政府 (蒋中正) / 中国共产党 (民国三十六年)",
    "events": [
      {
        "title": "刘邓大军强行千里跃进大别山大反攻大拉开",
        "category": "军事战役",
        "desc": "民国三十六年八月，晋冀鲁豫野战军司令员刘伯承、政委邓小平，奉党中央指示，率部强渡黄河，在无后方依仗下强行“千里跃进大别山”，突入敌后腹地。这一重大的军事战役奇袭，彻底打破了国民党军的战略合围，拉开了人民解放军大反攻之大幕，威震大中华。"
      }
    ]
  },
  {
    "year": 1948,
    "dynasty": "中华民国",
    "emperor": "国民政府 (蒋中正) / 中国共产党 (民国三十七年)",
    "events": [
      {
        "title": "辽沈淮海平津三大战略决战相继大举爆发",
        "category": "军事战役",
        "desc": "民国三十七年秋，在党中央与毛泽东主席的雄伟统帅决策下，中国人民解放军在东北、中原、华北平原隘口，相继发起了气吞山河之辽沈战役、淮海战役、平津战役三大战略决战。至此大局已定。这一伟大的军事战役总决战，歼灭了蒋军主力一百五十余万，奠定新中国诞生壁垒。"
      }
    ]
  },
  {
    "year": 1949,
    "dynasty": "中华人民共和国",
    "emperor": "毛泽东 (党和国家最高领导人)",
    "events": [
      {
        "title": "中华人民共和国开国大典毛泽东主席向全世界宣告成立",
        "category": "政权更迭",
        "desc": "1949年10月1日，中华人民共和国开国大典在北京天安门广场隆重举行。毛泽东主席在城楼上向全世界庄严宣告：“中华人民共和国中央人民政府今天成立了！”万众欢呼，红旗如海。这一划时代的政权更迭，标志着饱经沧桑之中国人民从此站起来了，大一统新时代大开。",
        "isMajor": true
      }
    ]
  },
  {
    "year": 1950,
    "dynasty": "中华人民共和国",
    "emperor": "毛泽东 (党和国家最高领导人)",
    "events": [
      {
        "title": "中国人民志愿军跨过鸭绿江英勇抗美援朝保家卫国",
        "category": "军事战役",
        "desc": "1950年10月，面对美国侵略军强行越过三八线、轰炸我国东北口岸之致命地缘威胁，中共中央毅然做出英明决策，命彭德怀为司令员，统率中国人民志愿军跨过鸭绿江，抗美援朝保家卫国。志愿军与美军在大平原与雪地隘口首度猛烈交火。这一重大的军事战役，拉开了反侵略序幕。"
      }
    ]
  },
  {
    "year": 1951,
    "dynasty": "中华人民共和国",
    "emperor": "毛泽东 (党和国家最高领导人)",
    "events": [
      {
        "title": "西藏和平解放大陆大一统基本宣告大功告成",
        "category": "政权更迭",
        "desc": "1951年5月，中央人民政府与西藏地方政府代表在北京正式签署了关于和平解放西藏办法之“十七条协议”，西藏宣告和平解放。十月，人民解放军在自耕农夹道欢迎下胜利进驻拉萨。这一重大的政权更迭与主权宣告，标志着中国大陆基本大一统达成，多民族空前凝聚。"
      }
    ]
  },
  {
    "year": 1952,
    "dynasty": "中华人民共和国",
    "emperor": "毛泽东 (党和国家最高领导人)",
    "events": [
      {
        "title": "荆江分洪枢纽大型古建工程完工保全两湖水利",
        "category": "古建工程",
        "desc": "1952年，为彻底清除两湖自耕农村落遭遇大决口决堤之万平天灾，新中国在毛泽东主席“将革命进行到底”精神指引下，在湖北沙市破土动工，大兴土木建成了规模宏伟之“荆江分洪工程”。工程大举组织了军民三十万，加筑防洪大坡。这一合理的古建工程不仅保全了民生，也彰显了国威。"
      }
    ]
  },
  {
    "year": 1953,
    "dynasty": "中华人民共和国",
    "emperor": "毛泽东 (党和国家最高领导人)",
    "events": [
      {
        "title": "抗美援朝胜利中朝代表在板门店正式签停战协定",
        "category": "军事战役",
        "desc": "1953年7月27日，经过两年的艰苦相持与隘口激战，中朝军队迫使傲慢的美军代表，在板门店正式签署了《朝鲜停战协定》，抗美援朝战争宣告取得伟大胜利。彭德怀自豪宣告西方侵略者在东方海岸架起大炮称霸时代一去不返。这一伟大的军事战役胜利，彻底奠定了新中国无敌之国际地位。",
        "isMajor": true
      }
    ]
  },
  {
    "year": 1954,
    "dynasty": "中华人民共和国",
    "emperor": "毛泽东 (党和国家最高领导人)",
    "events": [
      {
        "title": "第一届全国人民代表大会召开正式颁布五四宪法",
        "category": "政权更迭",
        "desc": "1954年9月，第一届全国人民代表大会第一次会议在北京隆重开幕。大会以无记名投票大一统通过并正式颁布了新中国首部宪法《中华人民共和国宪法》（五四宪法）。这一重大的政权更迭与国家根本法典创立，标志着新中国社会主义民主与法制制度的大一统确立，民心澎湃。"
      }
    ]
  },
  {
    "year": 1955,
    "dynasty": "中华人民共和国",
    "emperor": "毛泽东 (党和国家最高领导人)",
    "events": [
      {
        "title": "克拉玛依油田喷出工业原油大举发现新中国大油田",
        "category": "科技发明",
        "desc": "1955年10月，新中国首代地质勘探队在新疆克拉玛依荒壁之黑油山旁，大举喷出了工业级高产原油，惊人地发现了新中国首个超级大油田。这一伟大的科技发明与工业大发现，彻底击碎了西方所谓“中国无油论”之偏见，为新中国重工业化与军事国防大跃进提供了无可替代的能源保障。"
      }
    ]
  },
  {
    "year": 1956,
    "dynasty": "中华人民共和国",
    "emperor": "毛泽东 (党和国家最高领导人)",
    "events": [
      {
        "title": "首批解放牌载重汽车于吉林长春装配成功并下线",
        "category": "科技发明",
        "desc": "1956年7月，在长春第一汽车制造厂全体近代产业工人之无私大举奋斗下，新中国首批完全自主组装生产之“解放牌”载重汽车，正式装配成功并隆重走下流水线。这一伟大的科技发明与工业突破，标志着新中国自主汽车工业实现了从无到有之划时代跨越，民心大振。"
      }
    ]
  },
  {
    "year": 1957,
    "dynasty": "中华人民共和国",
    "emperor": "毛泽东 (党和国家最高领导人)",
    "events": [
      {
        "title": "武汉长江大桥大功告成天堑从此大举变通途",
        "category": "古建工程",
        "desc": "1957年10月，在苏联专家与中原名木石匠的紧密大举合作下，具有划时代意义的“武汉长江大桥”双层公路铁路大桥古建工程，正式提前大功告成通车。毛主席为此留下了“一桥飞架南北，天堑变通途”之伟大诗篇。这一合理的古建工程，彻底大一统连接了中国南北交通大命脉。"
      }
    ]
  },
  {
    "year": 1958,
    "dynasty": "中华人民共和国",
    "emperor": "毛泽东 (党和国家最高领导人)",
    "events": [
      {
        "title": "十三陵水库水利工程大兴土木数十万军民共建",
        "category": "古建工程",
        "desc": "1958年，为保全畿辅平原农田灌溉并防洪，北京市正式启动了昌平“十三陵水库”大型水利工程建设。工程大兴土木，毛泽东主席等中央领导亲自来到万平自耕农桑工地参加义务劳动，吸引了数十万军民自发扁担挑土。这一合理的古建工程完工，不仅极大地解决了水灾隐患，也弘扬了劳动文心。"
      }
    ]
  },
  {
    "year": 1959,
    "dynasty": "中华人民共和国",
    "emperor": "毛泽东 (党和国家最高领导人)",
    "events": [
      {
        "title": "黑龙江大庆油田喷油开发彻底摘掉中国贫油帽子",
        "category": "科技发明",
        "desc": "1959年9月，在松辽平原深处，新中国石油工人历经艰苦会战，在黑龙江大同镇附近油井大举喷出工业高产原油，向建国十周年献礼，特命名为“大庆油田”。铁人王进喜等工人大举发扬不怕死精神。这一科技发明的伟大胜利与油田开发，大举保障了新中国的能源主权与工业运转。"
      }
    ]
  },
  {
    "year": 1960,
    "dynasty": "中华人民共和国",
    "emperor": "毛泽东 (党和国家最高领导人)",
    "events": [
      {
        "title": "中国登山队首次从险峻北坡成功征服珠穆朗玛峰",
        "category": "科技发明",
        "desc": "1960年5月，中国登山队杰出勇士王富洲、贡布等三人，在风雪交加中，极其英勇地首次从极其艰险之珠穆朗玛峰北坡登顶成功，在地球之巅大举升起五星红旗。这一伟大的科技发明与体育探险壮举，捍卫了中国对喜马拉雅主权疆域的宣示，极大大举提振了全国人心理学士气。"
      }
    ]
  },
  {
    "year": 1961,
    "dynasty": "中华人民共和国",
    "emperor": "毛泽东 (党和国家最高领导人)",
    "events": [
      {
        "title": "清华大学等科研单位研制成功新中国首台数字计算机",
        "category": "科技发明",
        "desc": "1961年，在国家自然科学基金大举支持下，清华大学杰出教授与上海微电子研究所科研人员合力，排除万难研制成功了新中国首台近代电子数字计算机。该设备引进了西方先进的声学磁鼓技术。这一伟大的科技发明大突破，标志着中国在近代前沿电子计算科技领域迈出了重要一步。"
      }
    ]
  },
  {
    "year": 1962,
    "dynasty": "中华人民共和国",
    "emperor": "毛泽东 (党和国家最高领导人)",
    "events": [
      {
        "title": "中印边境自卫反击战爆发大军隘口全线横扫印军",
        "category": "军事战役",
        "desc": "1962年10月，面对印度侵略军对西藏与新疆边防防线的强行蚕食，中国边防大军奉命发起中印边境自卫反击战。清朝——不，中国官兵在极其恶劣的高原缺氧关隘，大举展开铁血反击，仅用时月余便全线大破印军主力，保全了国家神圣领土，展现了人民军队之无敌军威。"
      }
    ]
  },
  {
    "year": 1963,
    "dynasty": "中华人民共和国",
    "emperor": "毛泽东 (党和国家最高领导人)",
    "events": [
      {
        "title": "毛泽东主席发表向雷锋同志学习题词感召亿万",
        "category": "社会民生",
        "desc": "1963年3月，毛泽东主席欣然命笔，发表了“向雷锋同志学习”之伟大亲笔题词，全国各直省大举掀起了向因公殉职之雷锋同志学习的热潮。雷锋同志那全心全意为人民服务、乐于助人之高尚道德文心，成为感召亿万新中国青年在社会主义桑蚕农桑岗位上无私奉献的精神灯塔。"
      }
    ]
  },
  {
    "year": 1964,
    "dynasty": "中华人民共和国",
    "emperor": "毛泽东 (党和国家最高领导人)",
    "events": [
      {
        "title": "中国首颗原子弹在新疆罗布泊戈壁滩试爆成功",
        "category": "科技发明",
        "desc": "1964年10月16日15时，在新疆罗布泊茫茫戈壁滩深处，中国首颗自行研制之“原子弹”试爆成功，升起巨大的蘑菇云。国防尖端科技发明惊天大突破，中国正式拥有核反击力量。这一重大的科技发明胜利，彻底大举打破了超级大国的核垄断与核威胁，功勋震古烁今。",
        "isMajor": true
      }
    ]
  },
  {
    "year": 1965,
    "dynasty": "中华人民共和国",
    "emperor": "毛泽东 (党和国家最高领导人)",
    "events": [
      {
        "title": "中国科学家在世界上首次人工合成结晶牛胰岛素",
        "category": "科技发明",
        "desc": "1965年9月，中国科学院生物化学研究所等单位合力，在世界上首次大举成功实现了“人工合成结晶牛胰岛素”之伟大医学科技突破，经测试生物活性完全等同于天然胰岛素。这一伟大的生物科技发明，是中国近代自然科学史上里程碑式之斐然建树，震惊全球学术界，功存宇宙。"
      }
    ]
  },
  {
    "year": 1966,
    "dynasty": "中华人民共和国",
    "emperor": "毛泽东 (党和国家最高领导人)",
    "events": [
      {
        "title": "中国首枚导弹核武器试验在新疆戈壁取得大成功",
        "category": "科技发明",
        "desc": "1966年10月，新中国首枚“导弹核武器”结合试验在西北戈壁靶场取得圆满大成功，导弹携核弹头精准命中预定隘口目标并爆炸。这一伟大的科技发明与海疆防务飞跃，标志着新中国正式拥有了实战化的核威慑打击能力，大一统巩固了共和国海陆空国防安全生命线。"
      }
    ]
  },
  {
    "year": 1967,
    "dynasty": "中华人民共和国",
    "emperor": "毛泽东 (党和国家最高领导人)",
    "events": [
      {
        "title": "中国首颗氢弹在新疆罗布泊高空试爆大获成功",
        "category": "科技发明",
        "desc": "1967年6月17日，在新疆罗布泊上空，中国首颗自行研发之“氢弹”由轰炸机空投试爆大获成功。中国实现从原子弹到氢弹跨越仅用时两年八个月，速度创世界奇迹。这一重大的科技发明与军工成就，进一步巩固了国防地缘主权，给在大西北关隘防守的志愿军将士以极大提振。"
      }
    ]
  },
  {
    "year": 1968,
    "dynasty": "中华人民共和国",
    "emperor": "毛泽东 (党和国家最高领导人)",
    "events": [
      {
        "title": "南京长江大桥双层公路铁路古建工程完工通车",
        "category": "古建工程",
        "desc": "1968年12月，由我国大举自行设计、完全独立动工修建之“南京长江大桥”双层铁路公路大桥，历经八载血战，正式宣告大功告成通车。大桥采用先进的钢桁梁榫卯营造，宛如雨后长虹横跨大江。这一伟大的古建工程胜利，彻底打破了外资阻断，为华东大宗商贸流向插上翅膀。"
      }
    ]
  },
  {
    "year": 1969,
    "dynasty": "中华人民共和国",
    "emperor": "毛泽东 (党和国家最高领导人)",
    "events": [
      {
        "title": "珍宝岛自卫反击战打响中国守军英勇痛击入侵",
        "category": "军事战役",
        "desc": "1969年3月，面对沙俄——不，面对苏军边防大兵强行入侵我黑龙江主权地缘珍宝岛，中国守军被迫发起珍宝岛自卫反击战。人民解放军战将不畏苏军装甲车，在江面隘口大举开火反击，成功粉碎了强敌蚕食阴谋，誓死捍卫了国家主权，展现了华夏儿女宁死不屈之傲骨文心。"
      }
    ]
  },
  {
    "year": 1970,
    "dynasty": "中华人民共和国",
    "emperor": "毛泽东 (党和国家最高领导人)",
    "events": [
      {
        "title": "东方红一号卫星发射成功太空唱响东方红旋律",
        "category": "科技发明",
        "desc": "1970年4月24日，新中国首颗人造地球卫星“东方红一号”，在酒泉发射要塞发射成功，卫星在太空大举唱响优美之《东方红》乐曲，中国成为世界上第五个独立发射卫星的国家。这一重大的科技发明大捷，标志着中国航天事业正式跨入宇宙纪元，大一统振奋了海内外中华文心。"
      }
    ]
  },
  {
    "year": 1971,
    "dynasty": "中华人民共和国",
    "emperor": "毛泽东 (党和国家最高领导人)",
    "events": [
      {
        "title": "新中国宣告恢复在联合国一切合法主权外交席位",
        "category": "外交朝贡",
        "desc": "1971年10月25日，第二十六届联合国大会以压倒性多数，通过了著名的第2758号决议，正式宣告“恢复中华人民共和国在联合国的一切合法主权席位”，并将蒋介石代表驱逐。这一划时代的外交朝贡与主权外交的伟大性胜利，标志着新中国大一统重返国际政治中心大舞台。"
      }
    ]
  },
  {
    "year": 1972,
    "dynasty": "中华人民共和国",
    "emperor": "毛泽东 (党和国家最高领导人)",
    "events": [
      {
        "title": "美国总统尼克松正式访华打破中外外交坚冰",
        "category": "文化交流",
        "desc": "1972年2月，美国总统尼克松起銮正式访问中国，毛泽东主席与其大举举行会晤，中英中法中日等建交狂潮宣告大开，中外关系重现生机。这一重大的文化交流与外交折冲，彻底打破了长达二十余年之冷战孤立坚冰，极大改变了全球冷战地缘博弈大格局，功在当代。"
      }
    ]
  },
  {
    "year": 1973,
    "dynasty": "中华人民共和国",
    "emperor": "毛泽东 (党和国家最高领导人)",
    "events": [
      {
        "title": "杰出科学家袁隆平成功培育出首代籼型杂交水稻",
        "category": "科技发明",
        "desc": "1973年，江西——不，湖南杰出农学家袁隆平，历经数平艰苦科研，大举成功培育出了世界上首代高产“籼型杂交水稻”，大举提高了粮食亩产量。这一伟大的农业科技发明突破，大举解决了数亿人民的温饱生计，对于巩固新中国小农自耕农桑生计具有无可比拟的全球贡献。"
      }
    ]
  },
  {
    "year": 1974,
    "dynasty": "中华人民共和国",
    "emperor": "毛泽东 (党和国家最高领导人)",
    "events": [
      {
        "title": "西沙群岛自卫反击战大捷中国海军痛击南越军队",
        "category": "军事战役",
        "desc": "1974年1月，面对南越西贡政权悍然侵占我南海岛礁、枪击自耕农，中国南海舰队奉命发起西沙群岛自卫反击战。海军指战员在极其简陋装备下英勇决战，大破敌军舰队，生擒南越守军，全线收复三岛。这一重大的军事战役胜利，彻底大平定了南海挑衅，保全了神圣海防主权。"
      }
    ]
  },
  {
    "year": 1975,
    "dynasty": "中华人民共和国",
    "emperor": "毛泽东 (党和国家最高领导人)",
    "events": [
      {
        "title": "新中国成功研制并发射首颗返回式人造地球卫星",
        "category": "科技发明",
        "desc": "1975年11月，在钱学森等杰出科学家主持下，中国大举研制并成功发射了首颗“返回式人造地球卫星”，在完成预定科学测绘后，卫星大举安全返回预定降落场，使中国成为全球第三个掌握返回卫星技术的国家。这一重大的科技发明与航天成就，进一步夯实了国防要塞。"
      }
    ]
  },
  {
    "year": 1976,
    "dynasty": "中华人民共和国",
    "emperor": "华国锋 (党和国家最高领导人)",
    "events": [
      {
        "title": "毛泽东逝世唐山爆发大地震清算四人帮篡党",
        "category": "政权更迭",
        "desc": "1976年，新中国历经空前动荡。七月唐山爆发百年不遇特大强烈大地震，数十万平民不幸遇难。九月，一代伟人毛泽东主席与朱德、周恩来相继病逝，举国大恸。十月，华国锋等下铁血决心，大平定“四人帮”篡党夺权阴谋。这一重大的政权更迭，标志着动荡岁月终结，新纪元开启。"
      }
    ]
  },
  {
    "year": 1977,
    "dynasty": "中华人民共和国",
    "emperor": "华国锋 (党和国家最高领导人)",
    "events": [
      {
        "title": "高考正式恢复五百七十万士子进考场文心大振",
        "category": "科举儒典",
        "desc": "1977年冬，在党中央与邓小平的直接推动下，因动荡中断十载的全国“高考”制度正式大举宣告恢复，五百七十万自耕农与青年士子激动地踏入考场，回归科学公平。这一科举儒典铁血改革动作，彻底大一统振奋了被压抑的华夏文心，为中国改革开放大业储备了无穷贤俊。"
      }
    ]
  },
  {
    "year": 1978,
    "dynasty": "中华人民共和国",
    "emperor": "邓小平 (党和国家最高领导人)",
    "events": [
      {
        "title": "十一届三中全会召开确立改革开放伟大的历史转折",
        "category": "政权更迭",
        "desc": "1978年12月，中共十一届三中全会在北京隆重召开。全会以无与伦比之战略远见，彻底大举否定了左倾错误，正式做出将国家工作重心转移到以经济建设为中心的“改革开放”伟大历史性抉择。这一重大的政权更迭与思想解放，标志着新中国社会主义现代化建设扬帆启航。",
        "isMajor": true
      }
    ]
  },
  {
    "year": 1979,
    "dynasty": "中华人民共和国",
    "emperor": "邓小平 (党和国家最高领导人)",
    "events": [
      {
        "title": "中美建交中越自卫反击战大军攻占谅山大胜",
        "category": "外交朝贡",
        "desc": "1979年正月初一，中美两国正式建立大使级外交关系，中外文化交流再开新篇。二月，面对越南背信弃义挑衅边关，中国边防大军发起中越边境自卫反击战，清朝——不，解放军将士大破敌军谅山防线，取得军事战役大胜。这一合理的军事与外交朝贡主权博弈，维护了国家安全。"
      }
    ]
  },
  {
    "year": 1980,
    "dynasty": "中华人民共和国",
    "emperor": "邓小平 (党和国家最高领导人)",
    "events": [
      {
        "title": "深圳珠海汕头厦门设立首批经济特区对外招商",
        "category": "商业贸易",
        "desc": "1980年8月，在邓小平的直接画圈指引下，全国人大正式批准在广东深圳、珠海、汕头及福建厦门设立首批“经济特区”，大开优惠政策鼓励洋商入内开办工商业企业。这一划时代的商业贸易大改制开启，不仅极大地繁荣了沿海集市贸易，也为全国改革开放提供了金科玉律。"
      }
    ]
  },
  {
    "year": 1981,
    "dynasty": "中华人民共和国",
    "emperor": "邓小平 (党和国家最高领导人)",
    "events": [
      {
        "title": "中国女排荣获世界杯冠军大举振奋华夏儿女",
        "category": "社会民生",
        "desc": "1981年11月，在第三届世界杯女子排球赛中，中国女排姑娘在袁伟民指挥下顽强血战，以七战全胜之辉煌战绩首次荣获世界冠军，中国女排“拼搏精神”诞生。这一合理的社会民生正能量，在全国大集市引起了天崩地裂般欢呼，极大地大举凝聚并振奋了海内外中华儿女之文心。"
      }
    ]
  },
  {
    "year": 1982,
    "dynasty": "中华人民共和国",
    "emperor": "邓小平 (党和国家最高领导人)",
    "events": [
      {
        "title": "全国人大颁布八二宪法奠定社会主义法治壁垒",
        "category": "政权更迭",
        "desc": "1982年12月，第五届全国人民代表大会第五次会议，正式审议大一统通过并颁布了划时代的《中华人民共和国宪法》（八二宪法）。该宪法确立了改革开放和现代化建设的基本国策。这一重大的政权更迭与法典创立改制，为新时期的国家长治久安和商业贸易提供了终极法律制度屏障。"
      }
    ]
  },
  {
    "year": 1983,
    "dynasty": "中华人民共和国",
    "emperor": "邓小平 (党和国家最高领导人)",
    "events": [
      {
        "title": "首届中央电视台春节联欢晚会开播丰富文化",
        "category": "文化交流",
        "desc": "1983年除夕，首届“中央电视台春节联欢晚会”正式开播。晚会采用了划时代的热线点播与直播互动技术。这一重大的文化交流盛会，彻底打破了单调的节日氛围，大一统开辟了中国当代市民文化与电视艺术融合之先河，成为全球华夏儿女在除夕夜不可或缺之精神文心盛宴。"
      }
    ]
  },
  {
    "year": 1984,
    "dynasty": "中华人民共和国",
    "emperor": "邓小平 (党和国家最高领导人)",
    "events": [
      {
        "title": "许海峰在洛杉矶夺得中国首枚奥运金牌零的突破",
        "category": "社会民生",
        "desc": "1984年7月，在第23届洛杉矶奥运会上，中国神枪手许海峰大举顶住强敌压力，以无可匹敌之定力荣获男子自选手枪慢射冠军，夺得了中国奥运历史之首枚金牌，实现了“零的突破”。这一合理的社会民生大捷，让全世界听到了大中华崛起之雷鸣，彻底大举振奋了华夏脊梁。"
      }
    ]
  },
  {
    "year": 1985,
    "dynasty": "中华人民共和国",
    "emperor": "邓小平 (党和国家最高领导人)",
    "events": [
      {
        "title": "国务院决定成立海南省确立为全国最大经济特区",
        "category": "政权更迭",
        "desc": "1985年，为进一步扩大对外商业贸易并释放南海地缘活力，国务院下诏正式决定将海南岛从广东省大举划出，筹备设立“海南省”，并确立为全国面积最大、政策最优惠之省级“经济特区”，鼓励农桑与热带商贸。这一重大的政权更迭与区划改制，使得海南在大海潮头乘风破浪。"
      }
    ]
  },
  {
    "year": 1986,
    "dynasty": "中华人民共和国",
    "emperor": "邓小平 (党和国家最高领导人)",
    "events": [
      {
        "title": "全国推行九年制义务教育大举提升国民素质",
        "category": "社会民生",
        "desc": "1986年4月，第六届全国人大四次会议审议大一统通过并正式颁布《中华人民共和国义务教育法》，国家正式宣布在全国范围内逐步推行“九年制义务教育”，由财政全额拨专款。这一重大的社会民生人道德政，大举斩断了贫困代际传递，为国家近代化复兴奠定了最坚实之智力大坝。"
      }
    ]
  },
  {
    "year": 1987,
    "dynasty": "中华人民共和国",
    "emperor": "邓小平 (党和国家最高领导人)",
    "events": [
      {
        "title": "台湾当局开放台胞回乡探亲两岸隔绝状态被打破",
        "category": "文化交流",
        "desc": "1987年10月，在海内外中华儿女之共同期盼与大陆和平统一政策感召下，两岸正式打破了长达三十八平之绝对隔绝状态，台湾当局正式准许老兵及台胞回大陆回乡探亲。这一宏伟的文化交流与血脉重聚，在大集市引发千百人抱头大哭，极大地大举促进了海峡两岸的融冰交流。"
      }
    ]
  },
  {
    "year": 1988,
    "dynasty": "中华人民共和国",
    "emperor": "邓小平 (党和国家最高领导人)",
    "events": [
      {
        "title": "北京正负电子对撞机首次对撞成功科技大突破",
        "category": "科技发明",
        "desc": "1988年10月，在杰出物理学家朱洪元等主持下，由中科院高能物理研究所研制成功之“北京正负电子对撞机”，首次成功实现正负电子对撞，前沿科技发明惊天大突破。这一重大的科技发明胜利，使我国开始在高能物理对撞技术前沿占据世界一席之地，为近代科学插上翅膀。"
      }
    ]
  },
  {
    "year": 1989,
    "dynasty": "中华人民共和国",
    "emperor": "江泽民 (党和国家最高领导人)",
    "events": [
      {
        "title": "中苏正式恢复国家关系正常化戈尔巴乔夫访华",
        "category": "外交朝贡",
        "desc": "1989年5月，苏联总统戈尔巴乔夫正式起銮访问北京，与邓小平同志亲切大举握手，两国正式发表联合公报，恢复中苏两国关系正常化，中外文化交流再添佳话。这一合理的外交朝贡与主权外交史诗，标志着长达三十年之战略敌对彻底终结，安稳了我国漫长之北部边防防线。"
      }
    ]
  },
  {
    "year": 1990,
    "dynasty": "中华人民共和国",
    "emperor": "江泽民 (党和国家最高领导人)",
    "events": [
      {
        "title": "上海证券交易所正式营业金融改革大宗商贸提速",
        "category": "商业贸易",
        "desc": "1990年12月，经国务院正式特批，新中国首家“上海证券交易所”正式鸣锣开业营业。这标志着中国金融体制改革大举迈出了决定性的一步，大宗金银与资本可以通过股市大举大宗交易，极大繁荣了全国工商业，成为改革开放进一步走向深水区之不朽金融里程碑。"
      }
    ]
  },
  {
    "year": 1991,
    "dynasty": "中华人民共和国",
    "emperor": "江泽民 (党和国家最高领导人)",
    "events": [
      {
        "title": "秦山核电站并网发电结束大陆无核电历史科技跃",
        "category": "科技发明",
        "desc": "1991年12月，由我国大举自行设计、自行建造之“秦山核电站”在浙江海盐大功告成并正式并网发电，新中国结束了大陆无核电历史，前沿科技发明大跃进。核电站引进了声学核聚裂变先进科技。这一重大的科技发明与工业突破，为长江三角洲大宗工商业提供了洁净动力。"
      }
    ]
  },
  {
    "year": 1992,
    "dynasty": "中华人民共和国",
    "emperor": "江泽民 (党和国家最高领导人)",
    "events": [
      {
        "title": "中韩正式建立大使级外交关系东亚外交大解冻",
        "category": "外交朝贡",
        "desc": "1992年8月，中华人民共和国与大韩民国代表在北京正式签署建交公报，正式确立大使级外交关系，东亚地缘大解冻，两国商业贸易与文化交流神速大爆发。这一合理的重大的外交朝贡与主权博弈胜利，彻底大举清除了冷战时期遗留之半岛坚冰，大大开拓了我国外贸新要塞。"
      }
    ]
  },
  {
    "year": 1993,
    "dynasty": "中华人民共和国",
    "emperor": "江泽民 (党和国家最高领导人)",
    "events": [
      {
        "title": "汪辜会谈在新加坡举行确立九二共识两岸破冰",
        "category": "外交朝贡",
        "desc": "1993年4月，大陆海协会会长汪道涵与台湾海基会董事长辜振甫，在新加坡大举举行了历史性之“汪辜会谈”。会谈在“九二共识”绝对框架下大举签署四项协议。这一合理的外交朝贡与同胞文化交流，彻底确立了两岸民间和平沟通机制，使得台海地缘局势向和平安宁大举推进。"
      }
    ]
  },
  {
    "year": 1994,
    "dynasty": "中华人民共和国",
    "emperor": "江泽民 (党和国家最高领导人)",
    "events": [
      {
        "title": "湖北三峡水利枢纽特大防洪古建工程正式开工",
        "category": "古建工程",
        "desc": "1994年12月，举世瞩目之三峡水利枢纽防洪抗旱古建工程，在湖北宜昌正式大兴土木动工兴建。工程采用先进的石骨混凝土榫卯大坝科技发明，大举征发长江沿线自耕农及民夫数十万。这一极其宏伟的古建工程启动，对于根治长江千年洪涝灾害、保障华中民生生计具有万代功德。"
      }
    ]
  },
  {
    "year": 1995,
    "dynasty": "中华人民共和国",
    "emperor": "江泽民 (党和国家最高领导人)",
    "events": [
      {
        "title": "中国数字互联网网络技术正式向公众大举普及",
        "category": "科技发明",
        "desc": "1995年，在张朝阳等留美俊杰之积极大举推动下，中国首批近代数字互联网网络服务要塞正式在大都建立，并向全体公众普及。这一伟大的科技发明与文化交流盛事，彻底打破了传统通信与信息的时空隔绝，大一统掀起了席卷全华夏之信息化技术革命浪潮，功彪千秋。"
      }
    ]
  },
  {
    "year": 1996,
    "dynasty": "中华人民共和国",
    "emperor": "江泽民 (党和国家最高领导人)",
    "events": [
      {
        "title": "中国正式宣布暂停核试验为维护世界和平作贡献",
        "category": "外交朝贡",
        "desc": "1996年7月，在完成了最后一次核试验后，中华人民共和国政府庄严向全世界宣告：自1996年7月30日起，中国正式“暂停核试验”。这一伟大的外交朝贡与主权声明动作，得到了联合国及全球各国的极高赞誉，彰显了新中国作为负责任核大国、誓死大举维护世界和平之大担当。"
      }
    ]
  },
  {
    "year": 1997,
    "dynasty": "中华人民共和国",
    "emperor": "江泽民 (党和国家最高领导人)",
    "events": [
      {
        "title": "中国政府对香港恢复行使主权百年国耻洗雪",
        "category": "政权更迭",
        "desc": "1997年7月1日零时，中英两国政府在香港隆重举行主权交接大典。中国人民解放军驻港部队神速进驻，五星红旗在香港会展中心冉冉升起，香港正式大一统回归祖国，洗雪百年国耻。这一极其重大的政权更迭与外交胜利，标志着邓小平一国两制伟大构想宣告大功告成，功勋震天。",
        "isMajor": true
      }
    ]
  },
  {
    "year": 1998,
    "dynasty": "中华人民共和国",
    "emperor": "江泽民 (党和国家最高领导人)",
    "events": [
      {
        "title": "长江松花江遭遇百年大洪涝军民誓死并肩抗洪",
        "category": "社会民生",
        "desc": "1998年夏，长江、松花江流域遭遇百年不遇特大强烈洪涝决口，水浸百县，千万自耕农桑遭遇致命威胁，底层社会民生极为危机。江泽民同志亲临防洪大堤，调发解放军将士数万，以肉身死堵决口，取得了伟大抗洪胜利。这一重大的社会民生保卫战，凝聚了血肉文心，震撼乾坤。"
      }
    ]
  },
  {
    "year": 1999,
    "dynasty": "中华人民共和国",
    "emperor": "江泽民 (党和国家最高领导人)",
    "events": [
      {
        "title": "中国政府对澳门恢复行使主权大一统基业巩固",
        "category": "政权更迭",
        "desc": "1999年12月20日零时，中葡两国政府在澳门隆重举行主权交接大典。大中华恢复对澳门行使绝对主权，中国人民解放军驻澳部队胜利进驻执勤。这一极其重大的政权更迭与主权宣告，洗雪了数百年殖民沧桑，大一统巩固了多民族国家大团结，标志着国家大一统事业迈出决定性一步。",
        "isMajor": true
      }
    ]
  },
  {
    "year": 2000,
    "dynasty": "中华人民共和国",
    "emperor": "江泽民 (党和国家最高领导人)",
    "events": [
      {
        "title": "中国全面大举启动西气东输长输管线古建工程",
        "category": "古建工程",
        "desc": "2000年2月，为把大西北塔里木盆地之清洁天然气输送至东南沿海，新中国正式宣告全面启动“西气东输”特大长输管线古建工程。工程采用宏伟的钢管榫卯跨河跨山铺设。这一合理的古建工程与商业贸易大动脉告成，极大地大举促进了西部大开发与东部环保生计，功彪千古。"
      }
    ]
  }
]